enyday/__init__.py
enyday/api_client.py
enyday/api_response.py
enyday/configuration.py
enyday/exceptions.py
enyday/py.typed
enyday/rest.py
enyday/api/__init__.py
enyday/api/address_api.py
enyday/api/authorization_api.py
enyday/api/consumption_data_api.py
enyday/api/default_api.py
enyday/api/eloverblik_api.py
enyday/api/users_api.py
enyday/models/__init__.py
enyday/models/address.py
enyday/models/address_list.py
enyday/models/admin_btm.py
enyday/models/auth_request.py
enyday/models/auth_response.py
enyday/models/authorization.py
enyday/models/btm_details.py
enyday/models/common_consumption.py
enyday/models/common_production.py
enyday/models/community_consumption.py
enyday/models/consumption_address.py
enyday/models/consumption_data.py
enyday/models/consumption_member.py
enyday/models/consumption_status.py
enyday/models/hourly_price.py
enyday/models/invoice.py
enyday/models/invoice_list.py
enyday/models/nordpool_area.py
enyday/models/nordpool_average.py
enyday/models/nordpool_cost_data.py
enyday/models/nordpool_hour.py
enyday/models/period.py
enyday/models/power_data_list.py
enyday/models/power_data_point.py
enyday/models/preliminary_invoice.py
enyday/models/role.py
enyday/models/submeter.py
enyday/models/submeter_detail.py
enyday/models/user_btm.py
enyday/models/user_detail.py
enyday/models/user_details.py
enyday/test/__init__.py
enyday/test/test_address.py
enyday/test/test_address_api.py
enyday/test/test_address_list.py
enyday/test/test_admin_btm.py
enyday/test/test_auth_request.py
enyday/test/test_auth_response.py
enyday/test/test_authorization.py
enyday/test/test_authorization_api.py
enyday/test/test_btm_details.py
enyday/test/test_common_consumption.py
enyday/test/test_common_production.py
enyday/test/test_community_consumption.py
enyday/test/test_consumption_address.py
enyday/test/test_consumption_data.py
enyday/test/test_consumption_data_api.py
enyday/test/test_consumption_member.py
enyday/test/test_consumption_status.py
enyday/test/test_default_api.py
EnydayPy-1.0.5.dist-info/METADATA
EnydayPy-1.0.5.dist-info/WHEEL
EnydayPy-1.0.5.dist-info/top_level.txt
EnydayPy-1.0.5.dist-info/RECORD
