Metadata-Version: 2.2
Name: EnydayPy
Version: 1.0.5
Summary: Enyday API
Home-page: 
Author: OpenAPI Generator community
Author-email: OpenAPI Generator Community <team@openapitools.org>
License: MIT
Project-URL: Homepage, https://github.com/bruadam/enydaypy
Project-URL: Bug Tracker, https://github.com/bruadam/enydaypy/issues
Requires-Python: >=3.8
Dynamic: author
